amazon/opentelemetry/distro/_aws_attribute_keys.py
amazon/opentelemetry/distro/_aws_metric_attribute_generator.py
amazon/opentelemetry/distro/_aws_resource_attribute_configurator.py
amazon/opentelemetry/distro/_aws_span_processing_util.py
amazon/opentelemetry/distro/_utils.py
amazon/opentelemetry/distro/always_record_sampler.py
amazon/opentelemetry/distro/attribute_propagating_span_processor.py
amazon/opentelemetry/distro/attribute_propagating_span_processor_builder.py
amazon/opentelemetry/distro/aws_batch_unsampled_span_processor.py
amazon/opentelemetry/distro/aws_lambda_span_processor.py
amazon/opentelemetry/distro/aws_metric_attributes_span_exporter.py
amazon/opentelemetry/distro/aws_metric_attributes_span_exporter_builder.py
amazon/opentelemetry/distro/aws_opentelemetry_configurator.py
amazon/opentelemetry/distro/aws_opentelemetry_distro.py
amazon/opentelemetry/distro/aws_span_metrics_processor.py
amazon/opentelemetry/distro/aws_span_metrics_processor_builder.py
amazon/opentelemetry/distro/llo_handler.py
amazon/opentelemetry/distro/metric_attribute_generator.py
amazon/opentelemetry/distro/otlp_udp_exporter.py
amazon/opentelemetry/distro/scope_based_exporter.py
amazon/opentelemetry/distro/scope_based_filtering_view.py
amazon/opentelemetry/distro/sqs_url_parser.py
amazon/opentelemetry/distro/version.py
amazon/opentelemetry/distro/configuration/sql_dialect_keywords.json
amazon/opentelemetry/distro/exporter/otlp/aws/common/aws_auth_session.py
amazon/opentelemetry/distro/exporter/otlp/aws/logs/aws_batch_log_record_processor.py
amazon/opentelemetry/distro/exporter/otlp/aws/logs/otlp_aws_logs_exporter.py
amazon/opentelemetry/distro/exporter/otlp/aws/metrics/otlp_aws_emf_exporter.py
amazon/opentelemetry/distro/exporter/otlp/aws/traces/otlp_aws_span_exporter.py
amazon/opentelemetry/distro/patches/_bedrock_patches.py
amazon/opentelemetry/distro/patches/_botocore_patches.py
amazon/opentelemetry/distro/patches/_instrumentation_patch.py
yiyuanh_test_fork_aws_opentelemetry_distro-0.1.0.dist-info/METADATA
yiyuanh_test_fork_aws_opentelemetry_distro-0.1.0.dist-info/WHEEL
yiyuanh_test_fork_aws_opentelemetry_distro-0.1.0.dist-info/entry_points.txt
yiyuanh_test_fork_aws_opentelemetry_distro-0.1.0.dist-info/RECORD
